setup.cfg
setup.py
PySang.egg-info/PKG-INFO
PySang.egg-info/SOURCES.txt
PySang.egg-info/dependency_links.txt
PySang.egg-info/entry_points.txt
PySang.egg-info/top_level.txt
pysang/__init__.py
pysang/command_line.py
pysang/gui.py
pysang/gui_pyside.py
pysang/gui_tk.py
pysang/info.py
pysang/parser.py
pysang/plot.py
pysang/sequence_utils.py
pysang/data/FZ01_A12_096.ab1