Metadata-Version: 1.0
Name: PySang
Version: 0.3.9
Summary: Visualizer for Sanger chromatographs (ABI/AB1).
Home-page: https://github.com/iosonofabio/pysang
Author: Fabio Zanini
Author-email: fabio.zanini@tuebingen.mpg.de
License: Public domain
Platform: UNKNOWN
